<?xml version="1.0" encoding="UTF-8"?>
<MetaDataObject xmlns="http://v8.1c.ru/8.3/MDClasses" xmlns:app="http://v8.1c.ru/8.2/managed-application/core" xmlns:cfg="http://v8.1c.ru/8.1/data/enterprise/current-config" xmlns:cmi="http://v8.1c.ru/8.2/managed-application/cmi" xmlns:ent="http://v8.1c.ru/8.1/data/enterprise" xmlns:lf="http://v8.1c.ru/8.2/managed-application/logform" xmlns:style="http://v8.1c.ru/8.1/data/ui/style" xmlns:sys="http://v8.1c.ru/8.1/data/ui/fonts/system" xmlns:v8="http://v8.1c.ru/8.1/data/core" xmlns:v8ui="http://v8.1c.ru/8.1/data/ui" xmlns:web="http://v8.1c.ru/8.1/data/ui/colors/web" xmlns:win="http://v8.1c.ru/8.1/data/ui/colors/windows" xmlns:xen="http://v8.1c.ru/8.3/xcf/enums" xmlns:xpr="http://v8.1c.ru/8.3/xcf/predef" xmlns:xr="http://v8.1c.ru/8.3/xcf/readable" xmlns:xs="http://www.w3.org/2001/XMLSchema" xmlns:xsi="http://www.w3.org/2001/XMLSchema-instance" version="2.9">
	<ExchangePlan uuid="144f88be-e9c7-4c0b-817a-0a254245c601">
		<InternalInfo>
			<xr:ThisNode>9aac2508-c585-41b6-9ece-36b3a5a2a3ef</xr:ThisNode>
			<xr:GeneratedType name="ExchangePlanObject.Полный" category="Object">
				<xr:TypeId>a296f72a-6c02-4286-8f37-2a1226a11878</xr:TypeId>
				<xr:ValueId>40da5c73-6d54-49f7-b074-8b499ea05e40</xr:ValueId>
			</xr:GeneratedType>
			<xr:GeneratedType name="ExchangePlanRef.Полный" category="Ref">
				<xr:TypeId>855e0f7d-c560-4ef0-9385-c7e9da461232</xr:TypeId>
				<xr:ValueId>13c16923-7d46-4428-b1a9-755ddb43b70d</xr:ValueId>
			</xr:GeneratedType>
			<xr:GeneratedType name="ExchangePlanSelection.Полный" category="Selection">
				<xr:TypeId>1cf9f875-f4dc-462a-9dc2-8d699db9cc90</xr:TypeId>
				<xr:ValueId>adda1a1e-fd33-4053-a746-05ad75313c7f</xr:ValueId>
			</xr:GeneratedType>
			<xr:GeneratedType name="ExchangePlanList.Полный" category="List">
				<xr:TypeId>1f0e28cb-753b-492d-b395-8d9271738716</xr:TypeId>
				<xr:ValueId>f89920eb-3b7d-4d09-8e10-c9a938f521d3</xr:ValueId>
			</xr:GeneratedType>
			<xr:GeneratedType name="ExchangePlanManager.Полный" category="Manager">
				<xr:TypeId>e1f82500-a55f-4b1c-9420-dd37fd5a135a</xr:TypeId>
				<xr:ValueId>17c49960-a311-459b-a106-78c0755fc419</xr:ValueId>
			</xr:GeneratedType>
		</InternalInfo>
		<Properties>
			<Name>Полный</Name>
			<Synonym>
				<v8:item>
					<v8:lang>ru</v8:lang>
					<v8:content>Полный</v8:content>
				</v8:item>
			</Synonym>
			<Comment/>
			<UseStandardCommands>false</UseStandardCommands>
			<CodeLength>3</CodeLength>
			<CodeAllowedLength>Fixed</CodeAllowedLength>
			<DescriptionLength>100</DescriptionLength>
			<DefaultPresentation>AsDescription</DefaultPresentation>
			<EditType>InDialog</EditType>
			<QuickChoice>false</QuickChoice>
			<ChoiceMode>BothWays</ChoiceMode>
			<InputByString>
				<xr:Field>ExchangePlan.Полный.StandardAttribute.Description</xr:Field>
				<xr:Field>ExchangePlan.Полный.StandardAttribute.Code</xr:Field>
			</InputByString>
			<SearchStringModeOnInputByString>Begin</SearchStringModeOnInputByString>
			<FullTextSearchOnInputByString>DontUse</FullTextSearchOnInputByString>
			<ChoiceDataGetModeOnInputByString>Directly</ChoiceDataGetModeOnInputByString>
			<DefaultObjectForm>ExchangePlan.Полный.Form.ФормаУзла</DefaultObjectForm>
			<DefaultListForm>ExchangePlan.Полный.Form.ФормаСписка</DefaultListForm>
			<DefaultChoiceForm/>
			<AuxiliaryObjectForm/>
			<AuxiliaryListForm/>
			<AuxiliaryChoiceForm/>
			<Characteristics/>
			<BasedOn/>
			<DistributedInfoBase>true</DistributedInfoBase>
			<IncludeConfigurationExtensions>false</IncludeConfigurationExtensions>
			<CreateOnInput>DontUse</CreateOnInput>
			<ChoiceHistoryOnInput>Auto</ChoiceHistoryOnInput>
			<IncludeHelpInContents>false</IncludeHelpInContents>
			<DataLockFields/>
			<DataLockControlMode>Automatic</DataLockControlMode>
			<FullTextSearch>Use</FullTextSearch>
			<ObjectPresentation/>
			<ExtendedObjectPresentation/>
			<ListPresentation/>
			<ExtendedListPresentation/>
			<Explanation/>
			<DataHistory>DontUse</DataHistory>
			<UpdateDataHistoryImmediatelyAfterWrite>false</UpdateDataHistoryImmediatelyAfterWrite>
			<ExecuteAfterWriteDataHistoryVersionProcessing>false</ExecuteAfterWriteDataHistoryVersionProcessing>
		</Properties>
		<ChildObjects>
			<Form>ФормаСписка</Form>
			<Form>ФормаУзла</Form>
		</ChildObjects>
	</ExchangePlan>
</MetaDataObject>